table_step/__init__.py
table_step/_version.py
table_step/table.py
table_step/table_parameters.py
table_step/table_step.py
table_step/tk_table.py
table_step-2025.6.1.dist-info/licenses/AUTHORS.rst
table_step-2025.6.1.dist-info/licenses/LICENSE
table_step-2025.6.1.dist-info/METADATA
table_step-2025.6.1.dist-info/WHEEL
table_step-2025.6.1.dist-info/entry_points.txt
table_step-2025.6.1.dist-info/top_level.txt
table_step-2025.6.1.dist-info/zip-safe
table_step-2025.6.1.dist-info/RECORD
